error_consistency/__init__.py
error_consistency/consistency.py
error_consistency/containers.py
error_consistency/deep/FashionMNIST/processed/test.pt
error_consistency/deep/FashionMNIST/processed/training.pt
error_consistency/deep/FashionMNIST/raw/t10k-images-idx3-ubyte
error_consistency/deep/FashionMNIST/raw/t10k-images-idx3-ubyte.gz
error_consistency/deep/FashionMNIST/raw/t10k-labels-idx1-ubyte
error_consistency/deep/FashionMNIST/raw/t10k-labels-idx1-ubyte.gz
error_consistency/deep/FashionMNIST/raw/train-images-idx3-ubyte
error_consistency/deep/FashionMNIST/raw/train-images-idx3-ubyte.gz
error_consistency/deep/FashionMNIST/raw/train-labels-idx1-ubyte
error_consistency/deep/FashionMNIST/raw/train-labels-idx1-ubyte.gz
error_consistency/functional.py
error_consistency/model.py
error_consistency/parallel.py
error_consistency/random.py
error_consistency/testing/loading.py
error_consistency/utils.py
error_consistency-0.3.1.dist-info/LICENSE
error_consistency-0.3.1.dist-info/WHEEL
error_consistency-0.3.1.dist-info/METADATA
error_consistency-0.3.1.dist-info/RECORD
