Metadata-Version: 2.1
Name: error-consistency
Version: 0.3.1
Summary: 
Author: Derek M Berger
Author-email: dmberger.dev@gmail.com
Requires-Python: >=3.8,<3.9
Classifier: Programming Language :: Python :: 3
Classifier: Programming Language :: Python :: 3.8
Requires-Dist: matplotlib (>=3.3.4,<4.0.0)
Requires-Dist: numba (>=0.52.0,<0.53.0)
Requires-Dist: numpy (>=1.19.5,<2.0.0)
Requires-Dist: pandas (>=1.2.1,<2.0.0)
Requires-Dist: scikit-learn (>=0.24.1,<0.25.0)
Requires-Dist: seaborn (>=0.11.1,<0.12.0)
Requires-Dist: sphinx-rtd-theme (>=0.5.2,<0.6.0)
Requires-Dist: tqdm (>=4.56.0,<5.0.0)
Requires-Dist: typing-extensions (>=3.7.4,<4.0.0)
